[{"name":"Manchester United","logo":"https://media.api-sports.io/football/teams/33.png","founded":1878},{"name":"Newcastle","logo":"https://media.api-sports.io/football/teams/34.png","founded":1892},{"name":"Bournemouth","logo":"https://media.api-sports.io/football/teams/35.png","founded":1899},{"name":"Watford","logo":"https://media.api-sports.io/football/teams/38.png","founded":1881},{"name":"Wolves","logo":"https://media.api-sports.io/football/teams/39.png","founded":1877},{"name":"Liverpool","logo":"https://media.api-sports.io/football/teams/40.png","founded":1892},{"name":"Southampton","logo":"https://media.api-sports.io/football/teams/41.png","founded":1885},{"name":"Arsenal","logo":"https://media.api-sports.io/football/teams/42.png","founded":1886},{"name":"Burnley","logo":"https://media.api-sports.io/football/teams/44.png","founded":1882},{"name":"Everton","logo":"https://media.api-sports.io/football/teams/45.png","founded":1878},{"name":"Leicester","logo":"https://media.api-sports.io/football/teams/46.png","founded":1884},{"name":"Tottenham","logo":"https://media.api-sports.io/football/teams/47.png","founded":1882},{"name":"West Ham","logo":"https://media.api-sports.io/football/teams/48.png","founded":1895},{"name":"Chelsea","logo":"https://media.api-sports.io/football/teams/49.png","founded":1905},{"name":"Manchester City","logo":"https://media.api-sports.io/football/teams/50.png","founded":1880},{"name":"Brighton","logo":"https://media.api-sports.io/football/teams/51.png","founded":1901},{"name":"Crystal Palace","logo":"https://media.api-sports.io/football/teams/52.png","founded":1905},{"name":"Sheffield Utd","logo":"https://media.api-sports.io/football/teams/62.png","founded":1889},{"name":"Aston Villa","logo":"https://media.api-sports.io/football/teams/66.png","founded":1874},{"name":"Norwich","logo":"https://media.api-sports.io/football/teams/71.png","founded":1902}]